pexip/__init__.py
pexip/__main__.py
pexip/cli/argparser.py
pexip/cli/args.py
pexip/cli/definitions.py
pexip/client.py
pexip/config.py
pexip/core.py
pexip/definitions.py
pexip/exceptions.py
pexip/models.py
pexip/utils.py
pexip-0.2.5.dist-info/entry_points.txt
pexip-0.2.5.dist-info/WHEEL
pexip-0.2.5.dist-info/METADATA
pexip-0.2.5.dist-info/RECORD
